[
  {
    "developerType" : "Other",
    "count" : 21
  },
  {
    "developerType" : "Mobile developer",
    "count" : 14
  },
  {
    "developerType" : "NA",
    "count" : 13
  },
  {
    "developerType" : "Web developer",
    "count" : 43
  },
  {
    "developerType" : "Developer with a statistics or mathematics background",
    "count" : 6
  },
  {
    "developerType" : "Desktop applications developer",
    "count" : 10
  },
  {
    "developerType" : "Database administrator",
    "count" : 8
  }
]